{
    "openapi": "3.0.0",
    "info": {
        "title": "auth/v1/auth.proto",
        "version": "version not set"
    },
    "tags": [
        {
            "name": "AuthService"
        }
    ],
    "paths": {
        "/v1/exchange-code": {
            "post": {
                "operationId": "AuthService_ExchangeCode",
                "responses": {
                    "200": {
                        "description": "A successful response.",
                        "content": {
                            "application/json": {
                                "schema": {
                                    "$ref": "#/components/schemas/v1ExchangeCodeResponse"
                                }
                            }
                        }
                    },
                    "default": {
                        "description": "An unexpected error response.",
                        "content": {
                            "application/json": {
                                "schema": {
                                    "$ref": "#/components/schemas/rpcStatus"
                                }
                            }
                        }
                    }
                },
                "requestBody": {
                    "content": {
                        "application/json": {
                            "schema": {
                                "$ref": "#/components/schemas/v1ExchangeCodeRequest"
                            }
                        }
                    },
                    "required": true
                },
                "tags": [
                    "AuthService"
                ]
            }
        },
        "/v1/login": {
            "post": {
                "operationId": "AuthService_Login",
                "responses": {
                    "200": {
                        "description": "A successful response.",
                        "content": {
                            "application/json": {
                                "schema": {
                                    "$ref": "#/components/schemas/v1LoginResponse"
                                }
                            }
                        }
                    },
                    "default": {
                        "description": "An unexpected error response.",
                        "content": {
                            "application/json": {
                                "schema": {
                                    "$ref": "#/components/schemas/rpcStatus"
                                }
                            }
                        }
                    }
                },
                "requestBody": {
                    "content": {
                        "application/json": {
                            "schema": {
                                "$ref": "#/components/schemas/v1LoginRequest"
                            }
                        }
                    },
                    "required": true
                },
                "tags": [
                    "AuthService"
                ]
            }
        },
        "/v1/logout": {
            "post": {
                "operationId": "AuthService_Logout",
                "responses": {
                    "200": {
                        "description": "A successful response.",
                        "content": {
                            "application/json": {
                                "schema": {
                                    "$ref": "#/components/schemas/v1LogoutResponse"
                                }
                            }
                        }
                    },
                    "default": {
                        "description": "An unexpected error response.",
                        "content": {
                            "application/json": {
                                "schema": {
                                    "$ref": "#/components/schemas/rpcStatus"
                                }
                            }
                        }
                    }
                },
                "requestBody": {
                    "content": {
                        "application/json": {
                            "schema": {
                                "$ref": "#/components/schemas/v1LogoutRequest"
                            }
                        }
                    },
                    "required": true
                },
                "tags": [
                    "AuthService"
                ]
            }
        },
        "/v1/m2m-token": {
            "post": {
                "operationId": "AuthService_GetM2MToken",
                "responses": {
                    "200": {
                        "description": "A successful response.",
                        "content": {
                            "application/json": {
                                "schema": {
                                    "$ref": "#/components/schemas/v1GetM2MTokenResponse"
                                }
                            }
                        }
                    },
                    "default": {
                        "description": "An unexpected error response.",
                        "content": {
                            "application/json": {
                                "schema": {
                                    "$ref": "#/components/schemas/rpcStatus"
                                }
                            }
                        }
                    }
                },
                "requestBody": {
                    "content": {
                        "application/json": {
                            "schema": {
                                "$ref": "#/components/schemas/v1GetM2MTokenRequest"
                            }
                        }
                    },
                    "required": true
                },
                "tags": [
                    "AuthService"
                ]
            }
        },
        "/v1/refresh": {
            "post": {
                "operationId": "AuthService_RefreshToken",
                "responses": {
                    "200": {
                        "description": "A successful response.",
                        "content": {
                            "application/json": {
                                "schema": {
                                    "$ref": "#/components/schemas/v1RefreshTokenResponse"
                                }
                            }
                        }
                    },
                    "default": {
                        "description": "An unexpected error response.",
                        "content": {
                            "application/json": {
                                "schema": {
                                    "$ref": "#/components/schemas/rpcStatus"
                                }
                            }
                        }
                    }
                },
                "requestBody": {
                    "content": {
                        "application/json": {
                            "schema": {
                                "$ref": "#/components/schemas/v1RefreshTokenRequest"
                            }
                        }
                    },
                    "required": true
                },
                "tags": [
                    "AuthService"
                ]
            }
        },
        "/v1/revoke": {
            "post": {
                "operationId": "AuthService_RevokeToken",
                "responses": {
                    "200": {
                        "description": "A successful response.",
                        "content": {
                            "application/json": {
                                "schema": {
                                    "$ref": "#/components/schemas/v1RevokeTokenResponse"
                                }
                            }
                        }
                    },
                    "default": {
                        "description": "An unexpected error response.",
                        "content": {
                            "application/json": {
                                "schema": {
                                    "$ref": "#/components/schemas/rpcStatus"
                                }
                            }
                        }
                    }
                },
                "requestBody": {
                    "content": {
                        "application/json": {
                            "schema": {
                                "$ref": "#/components/schemas/v1RevokeTokenRequest"
                            }
                        }
                    },
                    "required": true
                },
                "tags": [
                    "AuthService"
                ]
            }
        },
        "/v1/verify": {
            "post": {
                "operationId": "AuthService_VerifyToken",
                "responses": {
                    "200": {
                        "description": "A successful response.",
                        "content": {
                            "application/json": {
                                "schema": {
                                    "$ref": "#/components/schemas/v1VerifyTokenResponse"
                                }
                            }
                        }
                    },
                    "default": {
                        "description": "An unexpected error response.",
                        "content": {
                            "application/json": {
                                "schema": {
                                    "$ref": "#/components/schemas/rpcStatus"
                                }
                            }
                        }
                    }
                },
                "requestBody": {
                    "content": {
                        "application/json": {
                            "schema": {
                                "$ref": "#/components/schemas/v1VerifyTokenRequest"
                            }
                        }
                    },
                    "required": true
                },
                "tags": [
                    "AuthService"
                ]
            }
        }
    },
    "components": {
        "schemas": {
            "protobufAny": {
                "type": "object",
                "properties": {
                    "@type": {
                        "type": "string"
                    }
                },
                "additionalProperties": {}
            },
            "rpcStatus": {
                "type": "object",
                "properties": {
                    "code": {
                        "type": "integer",
                        "format": "int32"
                    },
                    "message": {
                        "type": "string"
                    },
                    "details": {
                        "type": "array",
                        "items": {
                            "$ref": "#/components/schemas/protobufAny"
                        }
                    }
                }
            },
            "v1ExchangeCodeRequest": {
                "type": "object",
                "properties": {
                    "code": {
                        "type": "string"
                    },
                    "redirectUri": {
                        "type": "string"
                    }
                }
            },
            "v1ExchangeCodeResponse": {
                "type": "object",
                "properties": {
                    "userId": {
                        "type": "string"
                    },
                    "accessToken": {
                        "type": "string"
                    }
                }
            },
            "v1GetM2MTokenRequest": {
                "type": "object",
                "properties": {
                    "clientId": {
                        "type": "string"
                    },
                    "clientSecret": {
                        "type": "string"
                    }
                }
            },
            "v1GetM2MTokenResponse": {
                "type": "object",
                "properties": {
                    "accessToken": {
                        "type": "string"
                    }
                }
            },
            "v1LoginRequest": {
                "type": "object",
                "properties": {
                    "redirectUri": {
                        "type": "string"
                    }
                }
            },
            "v1LoginResponse": {
                "type": "object",
                "properties": {
                    "loginUrl": {
                        "type": "string"
                    }
                }
            },
            "v1LogoutRequest": {
                "type": "object",
                "properties": {
                    "returnTo": {
                        "type": "string"
                    }
                }
            },
            "v1LogoutResponse": {
                "type": "object",
                "properties": {
                    "logoutUrl": {
                        "type": "string"
                    }
                }
            },
            "v1RefreshTokenRequest": {
                "type": "object"
            },
            "v1RefreshTokenResponse": {
                "type": "object",
                "properties": {
                    "accessToken": {
                        "type": "string"
                    }
                }
            },
            "v1RevokeTokenRequest": {
                "type": "object"
            },
            "v1RevokeTokenResponse": {
                "type": "object"
            },
            "v1VerifyTokenRequest": {
                "type": "object"
            },
            "v1VerifyTokenResponse": {
                "type": "object",
                "properties": {
                    "userId": {
                        "type": "string"
                    }
                }
            }
        }
    }
}